webdataset/__init__.py
webdataset/autodecode.py
webdataset/bench.py
webdataset/cache.py
webdataset/cborsiterators.py
webdataset/compat.py
webdataset/downloader.py
webdataset/extradatasets.py
webdataset/filters.py
webdataset/gopen.py
webdataset/handlers.py
webdataset/mix.py
webdataset/multi.py
webdataset/pipeline.py
webdataset/pytorch.py
webdataset/shardlists.py
webdataset/tariterators.py
webdataset/tenbin.py
webdataset/typecheck.py
webdataset/utils.py
webdataset/writer.py
wids/__init__.py
wids/wids.py
wids/wids_bench.py
wids/wids_cleanup.py
wids/wids_dir.py
wids/wids_dl.py
wids/wids_index.py
wids/wids_lru.py
wids/wids_mmtar.py
wids/wids_specs.py
wids/wids_tar.py
webdataset-0.2.99.dist-info/LICENSE
webdataset-0.2.99.dist-info/METADATA
webdataset-0.2.99.dist-info/WHEEL
webdataset-0.2.99.dist-info/entry_points.txt
webdataset-0.2.99.dist-info/top_level.txt
webdataset-0.2.99.dist-info/RECORD
